Metadata-Version: 2.1
Name: slipit
Version: 1.0.1
Summary: slipit - Utility for creating archives with path traversal elements
Home-page: https://github.com/usdAG/slipit
Author: Tobias Neitzel (@qtc_de)
Classifier: Programming Language :: Python :: 3
Classifier: Operating System :: Unix
Classifier: License :: OSI Approved :: GNU General Public License v3 (GPLv3)
License-File: LICENSE
